xarray_subset_grid/__init__.py
xarray_subset_grid/_version.py
xarray_subset_grid/accessor.py
xarray_subset_grid/grid.py
xarray_subset_grid/selector.py
xarray_subset_grid/utils.py
xarray_subset_grid/grids/__init__.py
xarray_subset_grid/grids/fvcom_grid.py
xarray_subset_grid/grids/regular_grid.py
xarray_subset_grid/grids/regular_grid_2d.py
xarray_subset_grid/grids/selfe_grid.py
xarray_subset_grid/grids/sgrid.py
xarray_subset_grid/grids/ugrid.py
xarray_subset_grid/visualization/mpl_plotting.py
xarray_subset_grid-0.1.0.dist-info/licenses/LICENSE
xarray_subset_grid-0.1.0.dist-info/METADATA
xarray_subset_grid-0.1.0.dist-info/WHEEL
xarray_subset_grid-0.1.0.dist-info/top_level.txt
xarray_subset_grid-0.1.0.dist-info/RECORD
