Metadata-Version: 2.4
Name: xarray-subset-grid
Version: 0.1.0
Summary: Subset Xarray datasets in time and space
Author-email: Matthew Iannucci <matt.iannucci@tetratech.com>, "Christopher H. Barker" <chris.barker@noaa.gov>
License: BSD 3-Clause License
Project-URL: Homepage, https://github.com/asascience-open/xarray-subset-grid
Keywords: xarray
Classifier: Development Status :: 5 - Production/Stable
Classifier: Intended Audience :: Science/Research
Classifier: License :: OSI Approved :: BSD License
Classifier: Operating System :: OS Independent
Classifier: Programming Language :: Python
Classifier: Programming Language :: Python :: 3 :: Only
Classifier: Programming Language :: Python :: 3.10
Classifier: Programming Language :: Python :: 3.11
Classifier: Programming Language :: Python :: 3.12
Classifier: Programming Language :: Python :: 3.13
Classifier: Topic :: Scientific/Engineering
Requires-Python: >=3.10
License-File: LICENSE
Requires-Dist: cf-xarray
Requires-Dist: cftime
Requires-Dist: dask
Requires-Dist: netcdf4
Requires-Dist: numpy
Requires-Dist: xarray>=2024.6
Provides-Extra: dev
Requires-Dist: pre-commit; extra == "dev"
Requires-Dist: pyright; extra == "dev"
Requires-Dist: pytest; extra == "dev"
Requires-Dist: pytest-cov; extra == "dev"
Requires-Dist: ruff; extra == "dev"
Requires-Dist: sphinx; extra == "dev"
Requires-Dist: sphinx-rtd-theme; extra == "dev"
Provides-Extra: examples
Requires-Dist: fsspec; extra == "examples"
Requires-Dist: h5netcdf; extra == "examples"
Requires-Dist: matplotlib; extra == "examples"
Requires-Dist: s3fs; extra == "examples"
Requires-Dist: zarr<3; extra == "examples"
Dynamic: license-file
